AUTHORS
LICENSE
MANIFEST.in
README.rst
setup.py
./bin/vaccagui
./bin/vaccapanel
Vacca.egg-info/PKG-INFO
Vacca.egg-info/SOURCES.txt
Vacca.egg-info/dependency_links.txt
Vacca.egg-info/entry_points.txt
Vacca.egg-info/not-zip-safe
Vacca.egg-info/requires.txt
Vacca.egg-info/top_level.txt
vacca/CHANGES
vacca/VERSION
vacca/__init__.py
vacca/alarms.py
vacca/config.py
vacca/default.py
vacca/doc.py
vacca/grid.py
vacca/main.py
vacca/panel.py
vacca/plot.py
vacca/properties.py
vacca/synoptics.py
vacca/tree.py
vacca/utils.py
vacca/image/equips/icon-any.gif
vacca/image/equips/icon-serial.gif
vacca/image/icons/AlbaLogo.png
vacca/image/icons/Mambo-icon.png
vacca/image/icons/TangoLogo.png
vacca/image/icons/alba-entry.JPG
vacca/image/icons/author.png
vacca/image/icons/clear.png
vacca/image/icons/clock.png
vacca/image/icons/close.png
vacca/image/icons/closetab.png
vacca/image/icons/closetab2.png
vacca/image/icons/fileopen.png
vacca/image/icons/filesave.png
vacca/image/icons/filesaveas.png
vacca/image/icons/flash.png
vacca/image/icons/icons.qrc
vacca/image/icons/info.png
vacca/image/icons/nggshow.php.png
vacca/image/icons/panic.gif
vacca/image/icons/pc-icon.jpg
vacca/image/icons/profile.png
vacca/image/icons/refresh.png
vacca/image/icons/search.png
vacca/image/icons/vacca-splash.jpg
vacca/image/widgets/Archiving.png
vacca/image/widgets/BLGrid.jpg
vacca/image/widgets/DevicePanel.png
vacca/image/widgets/PressureTrend.jpg
vacca/image/widgets/ProfilePlot.jpg
vacca/image/widgets/Properties.png
vacca/image/widgets/Synoptic.png
vacca/image/widgets/Tree.png
vacca/image/widgets/VerticalGrid.jpg
vacca/ini/vaccagui/__init__.py
vacca/ini/vaccagui/default.ini